permission_storage_manager/__init__.py
permission_storage_manager/py.typed
permission_storage_manager/core/__init__.py
permission_storage_manager/core/base.py
permission_storage_manager/core/exceptions.py
permission_storage_manager/core/manager.py
permission_storage_manager/providers/__init__.py
permission_storage_manager/providers/file_provider.py
permission_storage_manager/providers/memory_provider.py
permission_storage_manager/providers/redis_provider.py
permission_storage_manager/utils/__init__.py
permission_storage_manager/utils/helpers.py
permission_storage_manager-1.0.2.dist-info/licenses/LICENSE
permission_storage_manager-1.0.2.dist-info/METADATA
permission_storage_manager-1.0.2.dist-info/WHEEL
permission_storage_manager-1.0.2.dist-info/entry_points.txt
permission_storage_manager-1.0.2.dist-info/top_level.txt
permission_storage_manager-1.0.2.dist-info/RECORD
