Metadata-Version: 2.4
Name: permission-storage-manager
Version: 1.0.2
Summary: A flexible, high-performance permission storage system for Python applications
Author-email: Fatih Emre <fatihemre@github.com>, Permission Storage Manager Team <support@permission-storage-manager.dev>
Maintainer-email: Fatih Emre <fatihemre@github.com>
License: MIT
Project-URL: Homepage, https://github.com/fatihemre/permission-storage-manager
Project-URL: Documentation, https://github.com/fatihemre/permission-storage-manager/tree/main/docs
Project-URL: Repository, https://github.com/fatihemre/permission-storage-manager.git
Project-URL: Bug Tracker, https://github.com/fatihemre/permission-storage-manager/issues
Project-URL: Source Code, https://github.com/fatihemre/permission-storage-manager
Project-URL: Changelog, https://github.com/fatihemre/permission-storage-manager/blob/main/CHANGELOG.md
Project-URL: Download, https://pypi.org/project/permission-storage-manager/#files
Keywords: permissions,authorization,session-management,redis,storage,async,security,rbac,access-control
Classifier: Development Status :: 5 - Production/Stable
Classifier: Intended Audience :: Developers
Classifier: License :: OSI Approved :: MIT License
Classifier: Operating System :: OS Independent
Classifier: Programming Language :: Python :: 3
Classifier: Programming Language :: Python :: 3.8
Classifier: Programming Language :: Python :: 3.9
Classifier: Programming Language :: Python :: 3.10
Classifier: Programming Language :: Python :: 3.11
Classifier: Programming Language :: Python :: 3.12
Classifier: Topic :: Software Development :: Libraries :: Python Modules
Classifier: Topic :: System :: Systems Administration :: Authentication/Directory
Classifier: Topic :: Security
Classifier: Framework :: AsyncIO
Classifier: Typing :: Typed
Requires-Python: >=3.8
License-File: LICENSE
Requires-Dist: redis>=4.0.0
Requires-Dist: pydantic>=2.0.0
Requires-Dist: structlog>=23.0.0
Requires-Dist: typing-extensions>=4.0.0; python_version < "3.9"
Provides-Extra: redis
Requires-Dist: redis>=4.0.0; extra == "redis"
Requires-Dist: hiredis>=2.0.0; extra == "redis"
Provides-Extra: all
Requires-Dist: redis>=4.0.0; extra == "all"
Requires-Dist: hiredis>=2.0.0; extra == "all"
Requires-Dist: pydantic>=2.0.0; extra == "all"
Requires-Dist: structlog>=23.0.0; extra == "all"
Requires-Dist: fastapi>=0.100.0; extra == "all"
Requires-Dist: uvicorn>=0.20.0; extra == "all"
Requires-Dist: celery>=5.3.0; extra == "all"
Provides-Extra: dev
Requires-Dist: pytest>=7.0.0; extra == "dev"
Requires-Dist: pytest-asyncio>=0.21.0; extra == "dev"
Requires-Dist: pytest-cov>=4.0.0; extra == "dev"
Requires-Dist: pytest-mock>=3.10.0; extra == "dev"
Requires-Dist: pytest-benchmark>=4.0.0; extra == "dev"
Requires-Dist: black>=23.0.0; extra == "dev"
Requires-Dist: isort>=5.12.0; extra == "dev"
Requires-Dist: mypy>=1.0.0; extra == "dev"
Requires-Dist: flake8>=6.0.0; extra == "dev"
Requires-Dist: pre-commit>=3.0.0; extra == "dev"
Requires-Dist: tox>=4.0.0; extra == "dev"
Requires-Dist: coverage>=7.0.0; extra == "dev"
Provides-Extra: docs
Requires-Dist: sphinx>=6.0.0; extra == "docs"
Requires-Dist: sphinx-rtd-theme>=1.2.0; extra == "docs"
Requires-Dist: myst-parser>=1.0.0; extra == "docs"
Requires-Dist: sphinx-autodoc-typehints>=1.23.0; extra == "docs"
Provides-Extra: test
Requires-Dist: pytest>=7.0.0; extra == "test"
Requires-Dist: pytest-asyncio>=0.21.0; extra == "test"
Requires-Dist: pytest-cov>=4.0.0; extra == "test"
Requires-Dist: pytest-mock>=3.10.0; extra == "test"
Requires-Dist: pytest-benchmark>=4.0.0; extra == "test"
Requires-Dist: coverage>=7.0.0; extra == "test"
Requires-Dist: redis-server; extra == "test"
Dynamic: license-file
